surya/__init__.py
surya/common/__init__.py
surya/common/adetr/decoder.py
surya/common/donut/encoder.py
surya/common/donut/processor.py
surya/common/load.py
surya/common/polygon.py
surya/common/predictor.py
surya/common/pretrained.py
surya/common/s3.py
surya/common/surya/__init__.py
surya/common/surya/config.py
surya/common/surya/decoder/__init__.py
surya/common/surya/decoder/config.py
surya/common/surya/embedder/__init__.py
surya/common/surya/encoder/__init__.py
surya/common/surya/encoder/config.py
surya/common/surya/flash_attn_utils.py
surya/common/surya/processor/__init__.py
surya/common/surya/processor/schema.py
surya/common/surya/processor/tokenizer.py
surya/common/surya/schema.py
surya/common/util.py
surya/common/xla.py
surya/debug/draw.py
surya/debug/fonts.py
surya/debug/katex.js
surya/debug/render_html.py
surya/debug/text.py
surya/detection/__init__.py
surya/detection/heatmap.py
surya/detection/loader.py
surya/detection/model/__init__.py
surya/detection/model/config.py
surya/detection/model/encoderdecoder.py
surya/detection/parallel.py
surya/detection/processor.py
surya/detection/schema.py
surya/detection/util.py
surya/foundation/__init__.py
surya/foundation/cache/__init__.py
surya/foundation/cache/dynamic_ops.py
surya/foundation/cache/static_ops.py
surya/foundation/loader.py
surya/foundation/util.py
surya/input/load.py
surya/input/processing.py
surya/layout/__init__.py
surya/layout/label.py
surya/layout/schema.py
surya/logging.py
surya/models.py
surya/ocr_error/__init__.py
surya/ocr_error/loader.py
surya/ocr_error/model/__init__.py
surya/ocr_error/model/config.py
surya/ocr_error/model/encoder.py
surya/ocr_error/schema.py
surya/ocr_error/tokenizer.py
surya/recognition/__init__.py
surya/recognition/languages.py
surya/recognition/postprocessing.py
surya/recognition/schema.py
surya/recognition/util.py
surya/scripts/__init__.py
surya/scripts/config.py
surya/scripts/detect_layout.py
surya/scripts/detect_text.py
surya/scripts/finetune_ocr.py
surya_ocr-0.17.1.dist-info/METADATA
surya_ocr-0.17.1.dist-info/WHEEL
surya_ocr-0.17.1.dist-info/entry_points.txt
surya_ocr-0.17.1.dist-info/licenses/LICENSE
surya_ocr-0.17.1.dist-info/RECORD
