Metadata-Version: 2.4
Name: surya-ocr
Version: 0.17.1
Summary: OCR, layout, reading order, and table recognition in 90+ languages
License: GPL-3.0-or-later
License-File: LICENSE
Keywords: ocr,pdf,text detection,text recognition,tables
Author: Vik Paruchuri
Author-email: vik.paruchuri@gmail.com
Requires-Python: >=3.10,<4.0
Classifier: License :: OSI Approved :: GNU General Public License v3 or later (GPLv3+)
Classifier: Programming Language :: Python :: 3
Classifier: Programming Language :: Python :: 3.10
Classifier: Programming Language :: Python :: 3.11
Classifier: Programming Language :: Python :: 3.12
Classifier: Programming Language :: Python :: 3.13
Classifier: Programming Language :: Python :: 3.14
Requires-Dist: click (>=8.1.8,<9.0.0)
Requires-Dist: einops (>=0.8.1,<0.9.0)
Requires-Dist: filetype (>=1.2.0,<2.0.0)
Requires-Dist: opencv-python-headless (==4.11.0.86)
Requires-Dist: pillow (>=10.2.0,<11.0.0)
Requires-Dist: platformdirs (>=4.3.6,<5.0.0)
Requires-Dist: pre-commit (>=4.2.0,<5.0.0)
Requires-Dist: pydantic (>=2.5.3,<3.0.0)
Requires-Dist: pydantic-settings (>=2.1.0,<3.0.0)
Requires-Dist: pypdfium2 (==4.30.0)
Requires-Dist: python-dotenv (>=1.0.0,<2.0.0)
Requires-Dist: torch (>=2.7.0,<3.0.0)
Requires-Dist: transformers (>=4.56.1)
Project-URL: Repository, https://github.com/VikParuchuri/surya
